[
  {
    "text": [
      [
        "וּדְבַ֔שׁ כַּאֲשֶׁ֥ר דִּבֶּ֛ר יְהֹוָ֥ה אֱלֹהֵֽי־אֲבֹתֶ֖יךָ לָֽךְ׃ וְהָיָה֮"
      ]
    ],
    "verses": [
      {
        "book": 5,
        "chapter": 27,
        "verse": 4
      }
    ],
    "aliyot": [],
    "isPetucha": false
  },
  {
    "text": [
      [
        "בְּעׇבְרְכֶ֣ם אֶת־הַיַּרְדֵּן֒ תָּקִ֜ימוּ אֶת־הָאֲבָנִ֣ים הָאֵ֗לֶּה"
      ]
    ],
    "verses": [],
    "aliyot": [],
    "isPetucha": false
  },
  {
    "text": [
      [
        "אֲשֶׁ֨ר אָנֹכִ֜י מְצַוֶּ֥ה אֶתְכֶ֛ם הַיּ֖וֹם בְּהַ֣ר עֵיבָ֑ל וְשַׂדְתָּ֥"
      ]
    ],
    "verses": [],
    "aliyot": [],
    "isPetucha": false
  },
  {
    "text": [
      [
        "אוֹתָ֖ם בַּשִּֽׂיד׃ וּבָנִ֤יתָ שָּׁם֙ מִזְבֵּ֔חַ לַיהֹוָ֖ה אֱלֹהֶ֑יךָ מִזְבַּ֣ח"
      ]
    ],
    "verses": [
      {
        "book": 5,
        "chapter": 27,
        "verse": 5
      }
    ],
    "aliyot": [],
    "isPetucha": false
  },
  {
    "text": [
      [
        "אֲבָנִ֔ים לֹא־תָנִ֥יף עֲלֵיהֶ֖ם בַּרְזֶֽל׃ אֲבָנִ֤ים שְׁלֵמוֹת֙ תִּבְנֶ֔ה"
      ]
    ],
    "verses": [
      {
        "book": 5,
        "chapter": 27,
        "verse": 6
      }
    ],
    "aliyot": [],
    "isPetucha": false
  },
  {
    "text": [
      [
        "אֶת־מִזְבַּ֖ח יְהֹוָ֣ה אֱלֹהֶ֑יךָ וְהַעֲלִ֤יתָ עָלָיו֙ עוֹלֹ֔ת לַיהֹוָ֖ה"
      ]
    ],
    "verses": [],
    "aliyot": [],
    "isPetucha": false
  },
  {
    "text": [
      [
        "אֱלֹהֶֽיךָ׃ וְזָבַחְתָּ֥ שְׁלָמִ֖ים וְאָכַ֣לְתָּ שָּׁ֑ם וְשָׂ֣מַחְתָּ֔ לִפְנֵ֖י"
      ]
    ],
    "verses": [
      {
        "book": 5,
        "chapter": 27,
        "verse": 7
      }
    ],
    "aliyot": [],
    "isPetucha": false
  },
  {
    "text": [
      [
        "יְהֹוָ֥ה אֱלֹהֶֽיךָ׃ וְכָתַבְתָּ֣ עַל־הָאֲבָנִ֗ים אֶֽת־כׇּל־דִּבְרֵ֛י"
      ]
    ],
    "verses": [
      {
        "book": 5,
        "chapter": 27,
        "verse": 8
      }
    ],
    "aliyot": [],
    "isPetucha": false
  },
  {
    "text": [
      [
        "הַתּוֹרָ֥ה הַזֹּ֖את בַּאֵ֥ר הֵיטֵֽב׃",
        " וַיְדַבֵּ֤ר"
      ]
    ],
    "verses": [
      {
        "book": 5,
        "chapter": 27,
        "verse": 9
      }
    ],
    "aliyot": [],
    "isPetucha": false
  },
  {
    "text": [
      [
        "מֹשֶׁה֙ וְהַכֹּהֲנִ֣ים הַלְוִיִּ֔ם אֶ֥ל כׇּל־יִשְׂרָאֵ֖ל לֵאמֹ֑ר הַסְכֵּ֤ת ׀"
      ]
    ],
    "verses": [],
    "aliyot": [],
    "isPetucha": false
  },
  {
    "text": [
      [
        "וּשְׁמַע֙ יִשְׂרָאֵ֔ל הַיּ֤וֹם הַזֶּה֙ נִהְיֵ֣יתָֽ לְעָ֔ם לַיהֹוָ֖ה אֱלֹהֶֽיךָ׃"
      ]
    ],
    "verses": [],
    "aliyot": [],
    "isPetucha": false
  },
  {
    "text": [
      [
        "וְשָׁ֣מַעְתָּ֔ בְּק֖וֹל יְהֹוָ֣ה אֱלֹהֶ֑יךָ וְעָשִׂ֤יתָ אֶת־מִצְוֺתָו֙ וְאֶת־"
      ]
    ],
    "verses": [
      {
        "book": 5,
        "chapter": 27,
        "verse": 10
      }
    ],
    "aliyot": [],
    "isPetucha": false
  },
  {
    "text": [
      [
        "חֻקָּ֔יו אֲשֶׁ֛ר אָנֹכִ֥י מְצַוְּךָ֖ הַיּֽוֹם׃",
        " וַיְצַ֤ו"
      ]
    ],
    "verses": [
      {
        "book": 5,
        "chapter": 27,
        "verse": 11
      }
    ],
    "aliyot": [
      {
        "standard": 5
      }
    ],
    "isPetucha": false
  },
  {
    "text": [
      [
        "מֹשֶׁה֙ אֶת־הָעָ֔ם בַּיּ֥וֹם הַה֖וּא לֵאמֹֽר׃ אֵ֠לֶּה יַֽעַמְד֞וּ"
      ]
    ],
    "verses": [
      {
        "book": 5,
        "chapter": 27,
        "verse": 12
      }
    ],
    "aliyot": [],
    "isPetucha": false
  },
  {
    "text": [
      [
        "לְבָרֵ֤ךְ אֶת־הָעָם֙ עַל־הַ֣ר גְּרִזִ֔ים בְּעׇבְרְכֶ֖ם אֶת־הַיַּרְדֵּ֑ן"
      ]
    ],
    "verses": [],
    "aliyot": [],
    "isPetucha": false
  },
  {
    "text": [
      [
        "שִׁמְעוֹן֙ וְלֵוִ֣י וִֽיהוּדָ֔ה וְיִשָּׂשכָ֖ר וְיוֹסֵ֥ף וּבִנְיָמִֽן׃ וְאֵ֛לֶּה"
      ]
    ],
    "verses": [
      {
        "book": 5,
        "chapter": 27,
        "verse": 13
      }
    ],
    "aliyot": [],
    "isPetucha": false
  },
  {
    "text": [
      [
        "יַֽעַמְד֥וּ עַל־הַקְּלָלָ֖ה בְּהַ֣ר עֵיבָ֑ל רְאוּבֵן֙ גָּ֣ד וְאָשֵׁ֔ר"
      ]
    ],
    "verses": [],
    "aliyot": [],
    "isPetucha": false
  },
  {
    "text": [
      [
        "וּזְבוּלֻ֖ן דָּ֥ן וְנַפְתָּלִֽי׃ וְעָנ֣וּ הַלְוִיִּ֗ם וְאָ֥מְר֛וּ אֶל־כׇּל־אִ֥ישׁ"
      ]
    ],
    "verses": [
      {
        "book": 5,
        "chapter": 27,
        "verse": 14
      }
    ],
    "aliyot": [],
    "isPetucha": false
  },
  {
    "text": [
      [
        "יִשְׂרָאֵ֖ל ק֥וֹל רָֽם׃",
        " אָר֣וּר"
      ]
    ],
    "verses": [
      {
        "book": 5,
        "chapter": 27,
        "verse": 15
      }
    ],
    "aliyot": [],
    "isPetucha": false
  },
  {
    "text": [
      [
        "הָאִ֡ישׁ אֲשֶׁ֣ר יַעֲשֶׂה֩ פֶ֨סֶל וּמַסֵּכָ֜ה תּוֹעֲבַ֣ת יְהֹוָ֗ה"
      ]
    ],
    "verses": [],
    "aliyot": [],
    "isPetucha": false
  },
  {
    "text": [
      [
        "מַעֲשֵׂ֛ה יְדֵ֥י חָרָ֖שׁ וְשָׂ֣ם בַּסָּ֑תֶר וְעָנ֧וּ כׇל־הָעָ֛ם וְאָמְר֖וּ"
      ]
    ],
    "verses": [],
    "aliyot": [],
    "isPetucha": false
  },
  {
    "text": [
      [
        "אָמֵֽן׃",
        " אָר֕וּר מַקְלֶ֥ה אָבִ֖יו וְאִמּ֑וֹ וְאָמַ֥ר"
      ]
    ],
    "verses": [
      {
        "book": 5,
        "chapter": 27,
        "verse": 16
      }
    ],
    "aliyot": [],
    "isPetucha": false
  },
  {
    "text": [
      [
        "כׇּל־הָעָ֖ם אָמֵֽן׃",
        " אָר֕וּר מַסִּ֖יג גְּב֣וּל רֵעֵ֑הוּ"
      ]
    ],
    "verses": [
      {
        "book": 5,
        "chapter": 27,
        "verse": 17
      }
    ],
    "aliyot": [],
    "isPetucha": false
  },
  {
    "text": [
      [
        "וְאָמַ֥ר כׇּל־הָעָ֖ם אָמֵֽן׃",
        " אָר֕וּר מַשְׁגֶּ֥ה"
      ]
    ],
    "verses": [
      {
        "book": 5,
        "chapter": 27,
        "verse": 18
      }
    ],
    "aliyot": [],
    "isPetucha": false
  },
  {
    "text": [
      [
        "עִוֵּ֖ר בַּדָּ֑רֶךְ וְאָמַ֥ר כׇּל־הָעָ֖ם אָמֵֽן׃",
        " אָר֗וּר"
      ]
    ],
    "verses": [
      {
        "book": 5,
        "chapter": 27,
        "verse": 19
      }
    ],
    "aliyot": [],
    "isPetucha": false
  },
  {
    "text": [
      [
        "מַטֶּ֛ה מִשְׁפַּ֥ט גֵּר־יָת֖וֹם וְאַלְמָנָ֑ה וְאָמַ֥ר כׇּל־הָעָ֖ם אָמֵֽן׃"
      ]
    ],
    "verses": [],
    "aliyot": [],
    "isPetucha": false
  },
  {
    "text": [
      [
        "אָר֗וּר שֹׁכֵב֙ עִם־אֵ֣שֶׁת אָבִ֔יו כִּ֥י גִלָּ֖ה כְּנַ֣ף אָבִ֑יו וְאָמַ֥ר"
      ]
    ],
    "verses": [
      {
        "book": 5,
        "chapter": 27,
        "verse": 20
      }
    ],
    "aliyot": [],
    "isPetucha": false
  },
  {
    "text": [
      [
        "כׇּל־הָעָ֖ם אָמֵֽן׃",
        " אָר֕וּר שֹׁכֵ֖ב עִם־כׇּל־"
      ]
    ],
    "verses": [
      {
        "book": 5,
        "chapter": 27,
        "verse": 21
      }
    ],
    "aliyot": [],
    "isPetucha": false
  },
  {
    "text": [
      [
        "בְּהֵמָ֑ה וְאָמַ֥ר כׇּל־הָעָ֖ם אָמֵֽן׃",
        " אָר֗וּר"
      ]
    ],
    "verses": [
      {
        "book": 5,
        "chapter": 27,
        "verse": 22
      }
    ],
    "aliyot": [],
    "isPetucha": false
  },
  {
    "text": [
      [
        "שֹׁכֵב֙ עִם־אֲחֹת֔וֹ בַּת־אָבִ֖יו א֣וֹ בַת־אִמּ֑וֹ וְאָמַ֥ר כׇּל־הָעָ֖ם"
      ]
    ],
    "verses": [],
    "aliyot": [],
    "isPetucha": false
  },
  {
    "text": [
      [
        "אָמֵֽן׃",
        " אָר֕וּר שֹׁכֵ֖ב עִם־חֹֽתַנְתּ֑וֹ וְאָמַ֥ר"
      ]
    ],
    "verses": [
      {
        "book": 5,
        "chapter": 27,
        "verse": 23
      }
    ],
    "aliyot": [],
    "isPetucha": false
  },
  {
    "text": [
      [
        "כׇּל־הָעָ֖ם אָמֵֽן׃",
        " אָר֕וּר מַכֵּ֥ה רֵעֵ֖הוּ"
      ]
    ],
    "verses": [
      {
        "book": 5,
        "chapter": 27,
        "verse": 24
      }
    ],
    "aliyot": [],
    "isPetucha": false
  },
  {
    "text": [
      [
        "בַּסָּ֑תֶר וְאָמַ֥ר כׇּל־הָעָ֖ם אָמֵֽן׃",
        " אָרוּר֙"
      ]
    ],
    "verses": [
      {
        "book": 5,
        "chapter": 27,
        "verse": 25
      }
    ],
    "aliyot": [],
    "isPetucha": false
  },
  {
    "text": [
      [
        "לֹקֵ֣חַ שֹׁ֔חַד לְהַכּ֥וֹת נֶ֖פֶשׁ דָּ֣ם נָקִ֑י וְאָמַ֥ר כׇּל־הָעָ֖ם"
      ]
    ],
    "verses": [],
    "aliyot": [],
    "isPetucha": false
  },
  {
    "text": [
      [
        "אָמֵֽן׃",
        " אָר֗וּר אֲשֶׁ֧ר לֹא־יָקִ֛ים"
      ]
    ],
    "verses": [
      {
        "book": 5,
        "chapter": 27,
        "verse": 26
      }
    ],
    "aliyot": [],
    "isPetucha": false
  },
  {
    "text": [
      [
        "אֶת־דִּבְרֵ֥י הַתּוֹרָֽה־הַזֹּ֖את לַעֲשׂ֣וֹת אוֹתָ֑ם וְאָמַ֥ר כׇּל־"
      ]
    ],
    "verses": [],
    "aliyot": [],
    "isPetucha": false
  },
  {
    "text": [
      [
        "הָעָ֖ם אָמֵֽן׃#(פ)"
      ]
    ],
    "verses": [],
    "aliyot": [],
    "isPetucha": true
  },
  {
    "text": [
      [
        "וְהָיָ֗ה אִם־שָׁמ֤וֹעַ תִּשְׁמַע֙ בְּקוֹל֙ יְהֹוָ֣ה אֱלֹהֶ֔יךָ"
      ]
    ],
    "verses": [
      {
        "book": 5,
        "chapter": 28,
        "verse": 1
      }
    ],
    "aliyot": [],
    "isPetucha": false
  },
  {
    "text": [
      [
        "לִשְׁמֹ֤ר לַעֲשׂוֹת֙ אֶת־כׇּל־מִצְוֺתָ֔יו אֲשֶׁ֛ר אָנֹכִ֥י מְצַוְּךָ֖"
      ]
    ],
    "verses": [],
    "aliyot": [],
    "isPetucha": false
  },
  {
    "text": [
      [
        "הַיּ֑וֹם וּנְתָ֨נְךָ֜ יְהֹוָ֤ה אֱלֹהֶ֙יךָ֙ עֶלְי֔וֹן עַ֖ל כׇּל־גּוֹיֵ֥י"
      ]
    ],
    "verses": [],
    "aliyot": [],
    "isPetucha": false
  },
  {
    "text": [
      [
        "הָאָֽרֶץ׃ וּבָ֧אוּ עָלֶ֛יךָ כׇּל־הַבְּרָכ֥וֹת הָאֵ֖לֶּה וְהִשִּׂיגֻ֑ךָ"
      ]
    ],
    "verses": [
      {
        "book": 5,
        "chapter": 28,
        "verse": 2
      }
    ],
    "aliyot": [],
    "isPetucha": false
  },
  {
    "text": [
      [
        "כִּ֣י תִשְׁמַ֔ע בְּק֖וֹל יְהֹוָ֥ה אֱלֹהֶֽיךָ׃ בָּר֥וּךְ אַתָּ֖ה בָּעִ֑יר"
      ]
    ],
    "verses": [
      {
        "book": 5,
        "chapter": 28,
        "verse": 3
      }
    ],
    "aliyot": [],
    "isPetucha": false
  }
]