[
  {
    "text": [
      [
        "וְקַֽח־לָ֑ךְ וְלֹֽא־יָדַ֣ע יַעֲקֹ֔ב כִּ֥י רָחֵ֖ל גְּנָבָֽתַם׃ וַיָּבֹ֨א לָבָ֜ן"
      ]
    ],
    "verses": [
      {
        "book": 1,
        "chapter": 31,
        "verse": 33
      }
    ],
    "aliyot": [],
    "isPetucha": false
  },
  {
    "text": [
      [
        "בְּאֹ֥הֶל יַעֲקֹ֣ב ׀ וּבְאֹ֣הֶל לֵאָ֗ה וּבְאֹ֛הֶל שְׁתֵּ֥י הָאֲמָהֹ֖ת"
      ]
    ],
    "verses": [],
    "aliyot": [],
    "isPetucha": false
  },
  {
    "text": [
      [
        "וְלֹ֣א מָצָ֑א וַיֵּצֵא֙ מֵאֹ֣הֶל לֵאָ֔ה וַיָּבֹ֖א בְּאֹ֥הֶל רָחֵֽל׃ וְרָחֵ֞ל"
      ]
    ],
    "verses": [
      {
        "book": 1,
        "chapter": 31,
        "verse": 34
      }
    ],
    "aliyot": [],
    "isPetucha": false
  },
  {
    "text": [
      [
        "לָקְחָ֣ה אֶת־הַתְּרָפִ֗ים וַתְּשִׂמֵ֛ם בְּכַ֥ר הַגָּמָ֖ל וַתֵּ֣שֶׁב"
      ]
    ],
    "verses": [],
    "aliyot": [],
    "isPetucha": false
  },
  {
    "text": [
      [
        "עֲלֵיהֶ֑ם וַיְמַשֵּׁ֥שׁ לָבָ֛ן אֶת־כׇּל־הָאֹ֖הֶל וְלֹ֥א מָצָֽא׃"
      ]
    ],
    "verses": [],
    "aliyot": [],
    "isPetucha": false
  },
  {
    "text": [
      [
        "וַתֹּ֣אמֶר אֶל־אָבִ֗יהָ אַל־יִ֙חַר֙ בְּעֵינֵ֣י אֲדֹנִ֔י כִּ֣י ל֤וֹא אוּכַל֙"
      ]
    ],
    "verses": [
      {
        "book": 1,
        "chapter": 31,
        "verse": 35
      }
    ],
    "aliyot": [],
    "isPetucha": false
  },
  {
    "text": [
      [
        "לָק֣וּם מִפָּנֶ֔יךָ כִּי־דֶ֥רֶךְ נָשִׁ֖ים לִ֑י וַיְחַפֵּ֕שׂ וְלֹ֥א מָצָ֖א"
      ]
    ],
    "verses": [],
    "aliyot": [],
    "isPetucha": false
  },
  {
    "text": [
      [
        "אֶת־הַתְּרָפִֽים׃ וַיִּ֥חַר לְיַעֲקֹ֖ב וַיָּ֣רֶב בְּלָבָ֑ן וַיַּ֤עַן יַעֲקֹב֙"
      ]
    ],
    "verses": [
      {
        "book": 1,
        "chapter": 31,
        "verse": 36
      }
    ],
    "aliyot": [],
    "isPetucha": false
  },
  {
    "text": [
      [
        "וַיֹּ֣אמֶר לְלָבָ֔ן מַה־פִּשְׁעִי֙ מַ֣ה חַטָּאתִ֔י כִּ֥י דָלַ֖קְתָּ אַחֲרָֽי׃"
      ]
    ],
    "verses": [],
    "aliyot": [],
    "isPetucha": false
  },
  {
    "text": [
      [
        "כִּֽי־מִשַּׁ֣שְׁתָּ אֶת־כׇּל־כֵּלַ֗י מַה־מָּצָ֙אתָ֙ מִכֹּ֣ל כְּלֵי־בֵיתֶ֔ךָ"
      ]
    ],
    "verses": [
      {
        "book": 1,
        "chapter": 31,
        "verse": 37
      }
    ],
    "aliyot": [],
    "isPetucha": false
  },
  {
    "text": [
      [
        "שִׂ֣ים כֹּ֔ה נֶ֥גֶד אַחַ֖י וְאַחֶ֑יךָ וְיוֹכִ֖יחוּ בֵּ֥ין שְׁנֵֽינוּ׃ זֶה֩"
      ]
    ],
    "verses": [
      {
        "book": 1,
        "chapter": 31,
        "verse": 38
      }
    ],
    "aliyot": [],
    "isPetucha": false
  },
  {
    "text": [
      [
        "עֶשְׂרִ֨ים שָׁנָ֤ה אָנֹכִי֙ עִמָּ֔ךְ רְחֵלֶ֥יךָ וְעִזֶּ֖יךָ לֹ֣א שִׁכֵּ֑לוּ"
      ]
    ],
    "verses": [],
    "aliyot": [],
    "isPetucha": false
  },
  {
    "text": [
      [
        "וְאֵילֵ֥י צֹאנְךָ֖ לֹ֥א אָכָֽלְתִּי׃ טְרֵפָה֙ לֹא־הֵבֵ֣אתִי אֵלֶ֔יךָ"
      ]
    ],
    "verses": [
      {
        "book": 1,
        "chapter": 31,
        "verse": 39
      }
    ],
    "aliyot": [],
    "isPetucha": false
  },
  {
    "text": [
      [
        "אָנֹכִ֣י אֲחַטֶּ֔נָּה מִיָּדִ֖י תְּבַקְשֶׁ֑נָּה גְּנֻֽבְתִ֣י י֔וֹם וּגְנֻֽבְתִ֖י לָֽיְלָה׃"
      ]
    ],
    "verses": [],
    "aliyot": [],
    "isPetucha": false
  },
  {
    "text": [
      [
        "הָיִ֧יתִי בַיּ֛וֹם אֲכָלַ֥נִי חֹ֖רֶב וְקֶ֣רַח בַּלָּ֑יְלָה וַתִּדַּ֥ד שְׁנָתִ֖י"
      ]
    ],
    "verses": [
      {
        "book": 1,
        "chapter": 31,
        "verse": 40
      }
    ],
    "aliyot": [],
    "isPetucha": false
  },
  {
    "text": [
      [
        "מֵֽעֵינָֽי׃ זֶה־לִּ֞י עֶשְׂרִ֣ים שָׁנָה֮ בְּבֵיתֶ֒ךָ֒ עֲבַדְתִּ֜יךָ אַרְבַּֽע־"
      ]
    ],
    "verses": [
      {
        "book": 1,
        "chapter": 31,
        "verse": 41
      }
    ],
    "aliyot": [],
    "isPetucha": false
  },
  {
    "text": [
      [
        "עֶשְׂרֵ֤ה שָׁנָה֙ בִּשְׁתֵּ֣י בְנֹתֶ֔יךָ וְשֵׁ֥שׁ שָׁנִ֖ים בְּצֹאנֶ֑ךָ"
      ]
    ],
    "verses": [],
    "aliyot": [],
    "isPetucha": false
  },
  {
    "text": [
      [
        "וַתַּחֲלֵ֥ף אֶת־מַשְׂכֻּרְתִּ֖י עֲשֶׂ֥רֶת מֹנִֽים׃ לוּלֵ֡י אֱלֹהֵ֣י אָבִי֩"
      ]
    ],
    "verses": [
      {
        "book": 1,
        "chapter": 31,
        "verse": 42
      }
    ],
    "aliyot": [],
    "isPetucha": false
  },
  {
    "text": [
      [
        "אֱלֹהֵ֨י אַבְרָהָ֜ם וּפַ֤חַד יִצְחָק֙ הָ֣יָה לִ֔י כִּ֥י עַתָּ֖ה רֵיקָ֣ם"
      ]
    ],
    "verses": [],
    "aliyot": [],
    "isPetucha": false
  },
  {
    "text": [
      [
        "שִׁלַּחְתָּ֑נִי אֶת־עׇנְיִ֞י וְאֶת־יְגִ֧יעַ כַּפַּ֛י רָאָ֥ה אֱלֹהִ֖ים וַיּ֥וֹכַח"
      ]
    ],
    "verses": [],
    "aliyot": [],
    "isPetucha": false
  },
  {
    "text": [
      [
        "אָֽמֶשׁ׃ וַיַּ֨עַן לָבָ֜ן וַיֹּ֣אמֶר אֶֽל־יַעֲקֹ֗ב הַבָּנ֨וֹת בְּנֹתַ֜י וְהַבָּנִ֤ים"
      ]
    ],
    "verses": [
      {
        "book": 1,
        "chapter": 31,
        "verse": 43
      }
    ],
    "aliyot": [
      {
        "standard": 7
      }
    ],
    "isPetucha": false
  },
  {
    "text": [
      [
        "בָּנַי֙ וְהַצֹּ֣אן צֹאנִ֔י וְכֹ֛ל אֲשֶׁר־אַתָּ֥ה רֹאֶ֖ה לִי־ה֑וּא וְלִבְנֹתַ֞י"
      ]
    ],
    "verses": [],
    "aliyot": [],
    "isPetucha": false
  },
  {
    "text": [
      [
        "מָֽה־אֶעֱשֶׂ֤ה לָאֵ֙לֶּה֙ הַיּ֔וֹם א֥וֹ לִבְנֵיהֶ֖ן אֲשֶׁ֥ר יָלָֽדוּ׃ וְעַתָּ֗ה"
      ]
    ],
    "verses": [
      {
        "book": 1,
        "chapter": 31,
        "verse": 44
      }
    ],
    "aliyot": [],
    "isPetucha": false
  },
  {
    "text": [
      [
        "לְכָ֛ה נִכְרְתָ֥ה בְרִ֖ית אֲנִ֣י וָאָ֑תָּה וְהָיָ֥ה לְעֵ֖ד בֵּינִ֥י וּבֵינֶֽךָ׃"
      ]
    ],
    "verses": [],
    "aliyot": [],
    "isPetucha": false
  },
  {
    "text": [
      [
        "וַיִּקַּ֥ח יַעֲקֹ֖ב אָ֑בֶן וַיְרִימֶ֖הָ מַצֵּבָֽה׃ וַיֹּ֨אמֶר יַעֲקֹ֤ב לְאֶחָיו֙"
      ]
    ],
    "verses": [
      {
        "book": 1,
        "chapter": 31,
        "verse": 45
      },
      {
        "book": 1,
        "chapter": 31,
        "verse": 46
      }
    ],
    "aliyot": [],
    "isPetucha": false
  },
  {
    "text": [
      [
        "לִקְט֣וּ אֲבָנִ֔ים וַיִּקְח֥וּ אֲבָנִ֖ים וַיַּֽעֲשׂוּ־גָ֑ל וַיֹּ֥אכְלוּ שָׁ֖ם עַל־"
      ]
    ],
    "verses": [],
    "aliyot": [],
    "isPetucha": false
  },
  {
    "text": [
      [
        "הַגָּֽל׃ וַיִּקְרָא־ל֣וֹ לָבָ֔ן יְגַ֖ר שָׂהֲדוּתָ֑א וְיַֽעֲקֹ֔ב קָ֥רָא ל֖וֹ"
      ]
    ],
    "verses": [
      {
        "book": 1,
        "chapter": 31,
        "verse": 47
      }
    ],
    "aliyot": [],
    "isPetucha": false
  },
  {
    "text": [
      [
        "גַּלְעֵֽד׃ וַיֹּ֣אמֶר לָבָ֔ן הַגַּ֨ל הַזֶּ֥ה עֵ֛ד בֵּינִ֥י וּבֵינְךָ֖ הַיּ֑וֹם עַל־"
      ]
    ],
    "verses": [
      {
        "book": 1,
        "chapter": 31,
        "verse": 48
      }
    ],
    "aliyot": [],
    "isPetucha": false
  },
  {
    "text": [
      [
        "כֵּ֥ן קָרָֽא־שְׁמ֖וֹ גַּלְעֵֽד׃ וְהַמִּצְפָּה֙ אֲשֶׁ֣ר אָמַ֔ר יִ֥צֶף יְהֹוָ֖ה"
      ]
    ],
    "verses": [
      {
        "book": 1,
        "chapter": 31,
        "verse": 49
      }
    ],
    "aliyot": [],
    "isPetucha": false
  },
  {
    "text": [
      [
        "בֵּינִ֣י וּבֵינֶ֑ךָ כִּ֥י נִסָּתֵ֖ר אִ֥ישׁ מֵרֵעֵֽהוּ׃ אִם־תְּעַנֶּ֣ה אֶת־בְּנֹתַ֗י"
      ]
    ],
    "verses": [
      {
        "book": 1,
        "chapter": 31,
        "verse": 50
      }
    ],
    "aliyot": [],
    "isPetucha": false
  },
  {
    "text": [
      [
        "וְאִם־תִּקַּ֤ח נָשִׁים֙ עַל־בְּנֹתַ֔י אֵ֥ין אִ֖ישׁ עִמָּ֑נוּ רְאֵ֕ה אֱלֹהִ֥ים"
      ]
    ],
    "verses": [],
    "aliyot": [],
    "isPetucha": false
  },
  {
    "text": [
      [
        "עֵ֖ד בֵּינִ֥י וּבֵינֶֽךָ׃ וַיֹּ֥אמֶר לָבָ֖ן לְיַעֲקֹ֑ב הִנֵּ֣ה ׀ הַגַּ֣ל הַזֶּ֗ה"
      ]
    ],
    "verses": [
      {
        "book": 1,
        "chapter": 31,
        "verse": 51
      }
    ],
    "aliyot": [],
    "isPetucha": false
  },
  {
    "text": [
      [
        "וְהִנֵּה֙ הַמַּצֵּבָ֔ה אֲשֶׁ֥ר יָרִ֖יתִי בֵּינִ֥י וּבֵינֶֽךָ׃ עֵ֚ד הַגַּ֣ל הַזֶּ֔ה"
      ]
    ],
    "verses": [
      {
        "book": 1,
        "chapter": 31,
        "verse": 52
      }
    ],
    "aliyot": [],
    "isPetucha": false
  },
  {
    "text": [
      [
        "וְעֵדָ֖ה הַמַּצֵּבָ֑ה אִם־אָ֗נִי לֹֽא־אֶעֱבֹ֤ר אֵלֶ֙יךָ֙ אֶת־הַגַּ֣ל הַזֶּ֔ה"
      ]
    ],
    "verses": [],
    "aliyot": [],
    "isPetucha": false
  },
  {
    "text": [
      [
        "וְאִם־אַ֠תָּ֠ה לֹא־תַעֲבֹ֨ר אֵלַ֜י אֶת־הַגַּ֥ל הַזֶּ֛ה וְאֶת־הַמַּצֵּבָ֥ה"
      ]
    ],
    "verses": [],
    "aliyot": [],
    "isPetucha": false
  },
  {
    "text": [
      [
        "הַזֹּ֖את לְרָעָֽה׃ אֱלֹהֵ֨י אַבְרָהָ֜ם וֵֽאלֹהֵ֤י נָחוֹר֙ יִשְׁפְּט֣וּ"
      ]
    ],
    "verses": [
      {
        "book": 1,
        "chapter": 31,
        "verse": 53
      }
    ],
    "aliyot": [],
    "isPetucha": false
  },
  {
    "text": [
      [
        "בֵינֵ֔ינוּ אֱלֹהֵ֖י אֲבִיהֶ֑ם וַיִּשָּׁבַ֣ע יַעֲקֹ֔ב בְּפַ֖חַד אָבִ֥יו"
      ]
    ],
    "verses": [],
    "aliyot": [],
    "isPetucha": false
  },
  {
    "text": [
      [
        "יִצְחָֽק׃ וַיִּזְבַּ֨ח יַעֲקֹ֥ב זֶ֙בַח֙ בָּהָ֔ר וַיִּקְרָ֥א לְאֶחָ֖יו לֶאֱכׇל־"
      ]
    ],
    "verses": [
      {
        "book": 1,
        "chapter": 31,
        "verse": 54
      }
    ],
    "aliyot": [],
    "isPetucha": false
  },
  {
    "text": [
      [
        "לָ֑חֶם וַיֹּ֣אכְלוּ לֶ֔חֶם וַיָּלִ֖ינוּ בָּהָֽר׃ וַיַּשְׁכֵּ֨ם לָבָ֜ן בַּבֹּ֗קֶר"
      ]
    ],
    "verses": [
      {
        "book": 1,
        "chapter": 32,
        "verse": 1
      }
    ],
    "aliyot": [
      {
        "standard": 8
      }
    ],
    "isPetucha": false
  },
  {
    "text": [
      [
        "וַיְנַשֵּׁ֧ק לְבָנָ֛יו וְלִבְנוֹתָ֖יו וַיְבָ֣רֶךְ אֶתְהֶ֑ם וַיֵּ֛לֶךְ וַיָּ֥שׇׁב"
      ]
    ],
    "verses": [],
    "aliyot": [],
    "isPetucha": false
  },
  {
    "text": [
      [
        "לָבָ֖ן לִמְקֹמֽוֹ׃ וְיַעֲקֹ֖ב הָלַ֣ךְ לְדַרְכּ֑וֹ וַיִּפְגְּעוּ־ב֖וֹ מַלְאֲכֵ֥י"
      ]
    ],
    "verses": [
      {
        "book": 1,
        "chapter": 32,
        "verse": 2
      }
    ],
    "aliyot": [],
    "isPetucha": false
  },
  {
    "text": [
      [
        "אֱלֹהִֽים׃ וַיֹּ֤אמֶר יַעֲקֹב֙ כַּאֲשֶׁ֣ר רָאָ֔ם מַחֲנֵ֥ה אֱלֹהִ֖ים זֶ֑ה"
      ]
    ],
    "verses": [
      {
        "book": 1,
        "chapter": 32,
        "verse": 3
      }
    ],
    "aliyot": [],
    "isPetucha": false
  }
]