[
  {
    "text": [
      [
        "וַיֹּ֤אמֶר אֲלֵהֶם֙ אַהֲרֹ֔ן פָּֽרְקוּ֙ נִזְמֵ֣י הַזָּהָ֔ב אֲשֶׁר֙ בְּאׇזְנֵ֣י"
      ]
    ],
    "verses": [
      {
        "book": 2,
        "chapter": 32,
        "verse": 2
      }
    ],
    "aliyot": [],
    "isPetucha": false
  },
  {
    "text": [
      [
        "נְשֵׁיכֶ֔ם בְּנֵיכֶ֖ם וּבְנֹתֵיכֶ֑ם וְהָבִ֖יאוּ אֵלָֽי׃ וַיִּתְפָּֽרְקוּ֙ כׇּל־"
      ]
    ],
    "verses": [
      {
        "book": 2,
        "chapter": 32,
        "verse": 3
      }
    ],
    "aliyot": [],
    "isPetucha": false
  },
  {
    "text": [
      [
        "הָעָ֔ם אֶת־נִזְמֵ֥י הַזָּהָ֖ב אֲשֶׁ֣ר בְּאׇזְנֵיהֶ֑ם וַיָּבִ֖יאוּ אֶֽל־"
      ]
    ],
    "verses": [],
    "aliyot": [],
    "isPetucha": false
  },
  {
    "text": [
      [
        "אַהֲרֹֽן׃ וַיִּקַּ֣ח מִיָּדָ֗ם וַיָּ֤צַר אֹתוֹ֙ בַּחֶ֔רֶט וַֽיַּעֲשֵׂ֖הוּ עֵ֣גֶל"
      ]
    ],
    "verses": [
      {
        "book": 2,
        "chapter": 32,
        "verse": 4
      }
    ],
    "aliyot": [],
    "isPetucha": false
  },
  {
    "text": [
      [
        "מַסֵּכָ֑ה וַיֹּ֣אמְר֔וּ אֵ֤לֶּה אֱלֹהֶ֙יךָ֙ יִשְׂרָאֵ֔ל אֲשֶׁ֥ר הֶעֱל֖וּךָ"
      ]
    ],
    "verses": [],
    "aliyot": [],
    "isPetucha": false
  },
  {
    "text": [
      [
        "מֵאֶ֥רֶץ מִצְרָֽיִם׃ וַיַּ֣רְא אַהֲרֹ֔ן וַיִּ֥בֶן מִזְבֵּ֖חַ לְפָנָ֑יו וַיִּקְרָ֤א"
      ]
    ],
    "verses": [
      {
        "book": 2,
        "chapter": 32,
        "verse": 5
      }
    ],
    "aliyot": [],
    "isPetucha": false
  },
  {
    "text": [
      [
        "אַֽהֲרֹן֙ וַיֹּאמַ֔ר חַ֥ג לַיהֹוָ֖ה מָחָֽר׃ וַיַּשְׁכִּ֙ימוּ֙ מִֽמׇּחֳרָ֔ת"
      ]
    ],
    "verses": [
      {
        "book": 2,
        "chapter": 32,
        "verse": 6
      }
    ],
    "aliyot": [],
    "isPetucha": false
  },
  {
    "text": [
      [
        "וַיַּעֲל֣וּ עֹלֹ֔ת וַיַּגִּ֖שׁוּ שְׁלָמִ֑ים וַיֵּ֤שֶׁב הָעָם֙ לֶֽאֱכֹ֣ל"
      ]
    ],
    "verses": [],
    "aliyot": [],
    "isPetucha": false
  },
  {
    "text": [
      [
        "וְשָׁת֔וֹ וַיָּקֻ֖מוּ לְצַחֵֽק׃#(פ)"
      ]
    ],
    "verses": [],
    "aliyot": [],
    "isPetucha": true
  },
  {
    "text": [
      [
        "וַיְדַבֵּ֥ר יְהֹוָ֖ה אֶל־מֹשֶׁ֑ה לֶךְ־רֵ֕ד כִּ֚י שִׁחֵ֣ת עַמְּךָ֔ אֲשֶׁ֥ר"
      ]
    ],
    "verses": [
      {
        "book": 2,
        "chapter": 32,
        "verse": 7
      }
    ],
    "aliyot": [],
    "isPetucha": false
  },
  {
    "text": [
      [
        "הֶעֱלֵ֖יתָ מֵאֶ֥רֶץ מִצְרָֽיִם׃ סָ֣רוּ מַהֵ֗ר מִן־הַדֶּ֙רֶךְ֙ אֲשֶׁ֣ר"
      ]
    ],
    "verses": [
      {
        "book": 2,
        "chapter": 32,
        "verse": 8
      }
    ],
    "aliyot": [],
    "isPetucha": false
  },
  {
    "text": [
      [
        "צִוִּיתִ֔ם עָשׂ֣וּ לָהֶ֔ם עֵ֖גֶל מַסֵּכָ֑ה וַיִּשְׁתַּֽחֲווּ־לוֹ֙ וַיִּזְבְּחוּ־"
      ]
    ],
    "verses": [],
    "aliyot": [],
    "isPetucha": false
  },
  {
    "text": [
      [
        "ל֔וֹ וַיֹּ֣אמְר֔וּ אֵ֤לֶּה אֱלֹהֶ֙יךָ֙ יִשְׂרָאֵ֔ל אֲשֶׁ֥ר הֶֽעֱל֖וּךָ"
      ]
    ],
    "verses": [],
    "aliyot": [],
    "isPetucha": false
  },
  {
    "text": [
      [
        "מֵאֶ֥רֶץ מִצְרָֽיִם׃ וַיֹּ֥אמֶר יְהֹוָ֖ה אֶל־מֹשֶׁ֑ה רָאִ֙יתִי֙ אֶת־"
      ]
    ],
    "verses": [
      {
        "book": 2,
        "chapter": 32,
        "verse": 9
      }
    ],
    "aliyot": [],
    "isPetucha": false
  },
  {
    "text": [
      [
        "הָעָ֣ם הַזֶּ֔ה וְהִנֵּ֥ה עַם־קְשֵׁה־עֹ֖רֶף הֽוּא׃ וְעַתָּה֙ הַנִּ֣יחָה"
      ]
    ],
    "verses": [
      {
        "book": 2,
        "chapter": 32,
        "verse": 10
      }
    ],
    "aliyot": [],
    "isPetucha": false
  },
  {
    "text": [
      [
        "לִּ֔י וְיִֽחַר־אַפִּ֥י בָהֶ֖ם וַאֲכַלֵּ֑ם וְאֶֽעֱשֶׂ֥ה אוֹתְךָ֖ לְג֥וֹי גָּדֽוֹל׃"
      ]
    ],
    "verses": [],
    "aliyot": [],
    "isPetucha": false
  },
  {
    "text": [
      [
        "וַיְחַ֣ל מֹשֶׁ֔ה אֶת־פְּנֵ֖י יְהֹוָ֣ה אֱלֹהָ֑יו וַיֹּ֗אמֶר לָמָ֤ה יְהֹוָה֙"
      ]
    ],
    "verses": [
      {
        "book": 2,
        "chapter": 32,
        "verse": 11
      }
    ],
    "aliyot": [],
    "isPetucha": false
  },
  {
    "text": [
      [
        "יֶחֱרֶ֤ה אַפְּךָ֙ בְּעַמֶּ֔ךָ אֲשֶׁ֤ר הוֹצֵ֙אתָ֙ מֵאֶ֣רֶץ מִצְרַ֔יִם"
      ]
    ],
    "verses": [],
    "aliyot": [],
    "isPetucha": false
  },
  {
    "text": [
      [
        "בְּכֹ֥חַ גָּד֖וֹל וּבְיָ֥ד חֲזָקָֽה׃ לָ֩מָּה֩ יֹאמְר֨וּ מִצְרַ֜יִם לֵאמֹ֗ר"
      ]
    ],
    "verses": [
      {
        "book": 2,
        "chapter": 32,
        "verse": 12
      }
    ],
    "aliyot": [],
    "isPetucha": false
  },
  {
    "text": [
      [
        "בְּרָעָ֤ה הֽוֹצִיאָם֙ לַהֲרֹ֤ג אֹתָם֙ בֶּֽהָרִ֔ים וּ֨לְכַלֹּתָ֔ם מֵעַ֖ל"
      ]
    ],
    "verses": [],
    "aliyot": [],
    "isPetucha": false
  },
  {
    "text": [
      [
        "פְּנֵ֣י הָֽאֲדָמָ֑ה שׁ֚וּב מֵחֲר֣וֹן אַפֶּ֔ךָ וְהִנָּחֵ֥ם עַל־הָרָעָ֖ה"
      ]
    ],
    "verses": [],
    "aliyot": [],
    "isPetucha": false
  },
  {
    "text": [
      [
        "לְעַמֶּֽךָ׃ זְכֹ֡ר לְאַבְרָהָם֩ לְיִצְחָ֨ק וּלְיִשְׂרָאֵ֜ל עֲבָדֶ֗יךָ"
      ]
    ],
    "verses": [
      {
        "book": 2,
        "chapter": 32,
        "verse": 13
      }
    ],
    "aliyot": [],
    "isPetucha": false
  },
  {
    "text": [
      [
        "אֲשֶׁ֨ר נִשְׁבַּ֣עְתָּ לָהֶם֮ בָּךְ֒ וַתְּדַבֵּ֣ר אֲלֵהֶ֔ם אַרְבֶּה֙ אֶֽת־"
      ]
    ],
    "verses": [],
    "aliyot": [],
    "isPetucha": false
  },
  {
    "text": [
      [
        "זַרְעֲכֶ֔ם כְּכוֹכְבֵ֖י הַשָּׁמָ֑יִם וְכׇל־הָאָ֨רֶץ הַזֹּ֜את אֲשֶׁ֣ר"
      ]
    ],
    "verses": [],
    "aliyot": [],
    "isPetucha": false
  },
  {
    "text": [
      [
        "אָמַ֗רְתִּי אֶתֵּן֙ לְזַרְעֲכֶ֔ם וְנָחֲל֖וּ לְעֹלָֽם׃ וַיִּנָּ֖חֶם יְהֹוָ֑ה עַל־"
      ]
    ],
    "verses": [
      {
        "book": 2,
        "chapter": 32,
        "verse": 14
      }
    ],
    "aliyot": [],
    "isPetucha": false
  },
  {
    "text": [
      [
        "הָ֣רָעָ֔ה אֲשֶׁ֥ר דִּבֶּ֖ר לַעֲשׂ֥וֹת לְעַמּֽוֹ׃#(פ)"
      ]
    ],
    "verses": [],
    "aliyot": [],
    "isPetucha": true
  },
  {
    "text": [
      [
        "וַיִּ֜פֶן וַיֵּ֤רֶד מֹשֶׁה֙ מִן־הָהָ֔ר וּשְׁנֵ֛י לֻחֹ֥ת הָעֵדֻ֖ת בְּיָד֑וֹ"
      ]
    ],
    "verses": [
      {
        "book": 2,
        "chapter": 32,
        "verse": 15
      }
    ],
    "aliyot": [],
    "isPetucha": false
  },
  {
    "text": [
      [
        "לֻחֹ֗ת כְּתֻבִים֙ מִשְּׁנֵ֣י עֶבְרֵיהֶ֔ם מִזֶּ֥ה וּמִזֶּ֖ה הֵ֥ם כְּתֻבִֽים׃"
      ]
    ],
    "verses": [],
    "aliyot": [],
    "isPetucha": false
  },
  {
    "text": [
      [
        "וְהַ֨לֻּחֹ֔ת מַעֲשֵׂ֥ה אֱלֹהִ֖ים הֵ֑מָּה וְהַמִּכְתָּ֗ב מִכְתַּ֤ב אֱלֹהִים֙"
      ]
    ],
    "verses": [
      {
        "book": 2,
        "chapter": 32,
        "verse": 16
      }
    ],
    "aliyot": [],
    "isPetucha": false
  },
  {
    "text": [
      [
        "ה֔וּא חָר֖וּת עַל־הַלֻּחֹֽת׃ וַיִּשְׁמַ֧ע יְהוֹשֻׁ֛עַ אֶת־ק֥וֹל"
      ]
    ],
    "verses": [
      {
        "book": 2,
        "chapter": 32,
        "verse": 17
      }
    ],
    "aliyot": [],
    "isPetucha": false
  },
  {
    "text": [
      [
        "הָעָ֖ם בְּרֵעֹ֑ה וַיֹּ֙אמֶר֙ אֶל־מֹשֶׁ֔ה ק֥וֹל מִלְחָמָ֖ה בַּֽמַּחֲנֶֽה׃"
      ]
    ],
    "verses": [],
    "aliyot": [],
    "isPetucha": false
  },
  {
    "text": [
      [
        "וַיֹּ֗אמֶר אֵ֥ין קוֹל֙ עֲנ֣וֹת גְּבוּרָ֔ה וְאֵ֥ין ק֖וֹל עֲנ֣וֹת חֲלוּשָׁ֑ה"
      ]
    ],
    "verses": [
      {
        "book": 2,
        "chapter": 32,
        "verse": 18
      }
    ],
    "aliyot": [],
    "isPetucha": false
  },
  {
    "text": [
      [
        "ק֣וֹל עַנּ֔וֹת אָנֹכִ֖י שֹׁמֵֽעַ׃ וַֽיְהִ֗י כַּאֲשֶׁ֤ר קָרַב֙ אֶל־הַֽמַּחֲנֶ֔ה"
      ]
    ],
    "verses": [
      {
        "book": 2,
        "chapter": 32,
        "verse": 19
      }
    ],
    "aliyot": [],
    "isPetucha": false
  },
  {
    "text": [
      [
        "וַיַּ֥רְא אֶת־הָעֵ֖גֶל וּמְחֹלֹ֑ת וַיִּֽחַר־אַ֣ף מֹשֶׁ֗ה וַיַּשְׁלֵ֤ךְ"
      ]
    ],
    "verses": [],
    "aliyot": [],
    "isPetucha": false
  },
  {
    "text": [
      [
        "מִיָּדָו֙ אֶת־הַלֻּחֹ֔ת וַיְשַׁבֵּ֥ר אֹתָ֖ם תַּ֥חַת הָהָֽר׃ וַיִּקַּ֞ח אֶת־"
      ]
    ],
    "verses": [
      {
        "book": 2,
        "chapter": 32,
        "verse": 20
      }
    ],
    "aliyot": [],
    "isPetucha": false
  },
  {
    "text": [
      [
        "הָעֵ֨גֶל אֲשֶׁ֤ר עָשׂוּ֙ וַיִּשְׂרֹ֣ף בָּאֵ֔שׁ וַיִּטְחַ֖ן עַ֣ד אֲשֶׁר־דָּ֑ק"
      ]
    ],
    "verses": [],
    "aliyot": [],
    "isPetucha": false
  },
  {
    "text": [
      [
        "וַיִּ֙זֶר֙ עַל־פְּנֵ֣י הַמַּ֔יִם וַיַּ֖שְׁקְ אֶת־בְּנֵ֥י יִשְׂרָאֵֽל׃ וַיֹּ֤אמֶר"
      ]
    ],
    "verses": [
      {
        "book": 2,
        "chapter": 32,
        "verse": 21
      }
    ],
    "aliyot": [],
    "isPetucha": false
  },
  {
    "text": [
      [
        "מֹשֶׁה֙ אֶֽל־אַהֲרֹ֔ן מֶֽה־עָשָׂ֥ה לְךָ֖ הָעָ֣ם הַזֶּ֑ה כִּֽי־הֵבֵ֥אתָ"
      ]
    ],
    "verses": [],
    "aliyot": [],
    "isPetucha": false
  },
  {
    "text": [
      [
        "עָלָ֖יו חֲטָאָ֥ה גְדֹלָֽה׃ וַיֹּ֣אמֶר אַהֲרֹ֔ן אַל־יִ֥חַר אַ֖ף אֲדֹנִ֑י"
      ]
    ],
    "verses": [
      {
        "book": 2,
        "chapter": 32,
        "verse": 22
      }
    ],
    "aliyot": [],
    "isPetucha": false
  },
  {
    "text": [
      [
        "אַתָּה֙ יָדַ֣עְתָּ אֶת־הָעָ֔ם כִּ֥י בְרָ֖ע הֽוּא׃ וַיֹּ֣אמְרוּ לִ֔י עֲשֵׂה־"
      ]
    ],
    "verses": [
      {
        "book": 2,
        "chapter": 32,
        "verse": 23
      }
    ],
    "aliyot": [],
    "isPetucha": false
  },
  {
    "text": [
      [
        "לָ֣נוּ אֱלֹהִ֔ים אֲשֶׁ֥ר יֵלְכ֖וּ לְפָנֵ֑ינוּ כִּי־זֶ֣ה ׀ מֹשֶׁ֣ה הָאִ֗ישׁ"
      ]
    ],
    "verses": [],
    "aliyot": [],
    "isPetucha": false
  },
  {
    "text": [
      [
        "אֲשֶׁ֤ר הֶֽעֱלָ֙נוּ֙ מֵאֶ֣רֶץ מִצְרַ֔יִם לֹ֥א יָדַ֖עְנוּ מֶה־הָ֥יָה לֽוֹ׃"
      ]
    ],
    "verses": [],
    "aliyot": [],
    "isPetucha": false
  }
]