[
  {
    "he": "בראשית",
    "ref": {
      "b": 1,
      "c": 1,
      "v": 1,
      "a": [
        1
      ]
    }
  },
  {
    "he": "נח",
    "ref": {
      "b": 1,
      "c": 6,
      "v": 9,
      "a": [
        1
      ]
    }
  },
  {
    "he": "לך לך",
    "ref": {
      "b": 1,
      "c": 12,
      "v": 1,
      "a": [
        1
      ]
    }
  },
  {
    "he": "וירא",
    "ref": {
      "b": 1,
      "c": 18,
      "v": 1,
      "a": [
        1
      ]
    }
  },
  {
    "he": "חיי שרה",
    "ref": {
      "b": 1,
      "c": 23,
      "v": 1,
      "a": [
        1
      ]
    }
  },
  {
    "he": "תולדות",
    "ref": {
      "b": 1,
      "c": 25,
      "v": 19,
      "a": [
        1
      ]
    }
  },
  {
    "he": "ויצא",
    "ref": {
      "b": 1,
      "c": 28,
      "v": 10,
      "a": [
        1
      ]
    }
  },
  {
    "he": "וישלח",
    "ref": {
      "b": 1,
      "c": 32,
      "v": 4,
      "a": [
        1
      ]
    }
  },
  {
    "he": "וישב",
    "ref": {
      "b": 1,
      "c": 37,
      "v": 1,
      "a": [
        1
      ]
    }
  },
  {
    "he": "מקץ",
    "ref": {
      "b": 1,
      "c": 41,
      "v": 1,
      "a": [
        1
      ]
    }
  },
  {
    "he": "ויגש",
    "ref": {
      "b": 1,
      "c": 44,
      "v": 18,
      "a": [
        1
      ]
    }
  },
  {
    "he": "ויחי",
    "ref": {
      "b": 1,
      "c": 47,
      "v": 28,
      "a": [
        1
      ]
    }
  },
  {
    "he": "שמות",
    "ref": {
      "b": 2,
      "c": 1,
      "v": 1,
      "a": [
        1
      ]
    }
  },
  {
    "he": "וארא",
    "ref": {
      "b": 2,
      "c": 6,
      "v": 2,
      "a": [
        1
      ]
    }
  },
  {
    "he": "בא",
    "ref": {
      "b": 2,
      "c": 10,
      "v": 1,
      "a": [
        1
      ]
    }
  },
  {
    "he": "בשלח",
    "ref": {
      "b": 2,
      "c": 13,
      "v": 17,
      "a": [
        1
      ]
    }
  },
  {
    "he": "יתרו",
    "ref": {
      "b": 2,
      "c": 18,
      "v": 1,
      "a": [
        1
      ]
    }
  },
  {
    "he": "משפטים",
    "ref": {
      "b": 2,
      "c": 21,
      "v": 1,
      "a": [
        1
      ]
    }
  },
  {
    "he": "תרומה",
    "ref": {
      "b": 2,
      "c": 25,
      "v": 1,
      "a": [
        1
      ]
    }
  },
  {
    "he": "תצוה",
    "ref": {
      "b": 2,
      "c": 27,
      "v": 20,
      "a": [
        1
      ]
    }
  },
  {
    "he": "כי תשא",
    "ref": {
      "b": 2,
      "c": 30,
      "v": 11,
      "a": [
        1
      ]
    }
  },
  {
    "he": "ויקהל",
    "ref": {
      "b": 2,
      "c": 35,
      "v": 1,
      "a": [
        1
      ]
    }
  },
  {
    "he": "פקודי",
    "ref": {
      "b": 2,
      "c": 38,
      "v": 21,
      "a": [
        1
      ]
    }
  },
  {
    "he": "ויקרא",
    "ref": {
      "b": 3,
      "c": 1,
      "v": 1,
      "a": [
        1
      ]
    }
  },
  {
    "he": "צו",
    "ref": {
      "b": 3,
      "c": 6,
      "v": 1,
      "a": [
        1
      ]
    }
  },
  {
    "he": "שמיני",
    "ref": {
      "b": 3,
      "c": 9,
      "v": 1,
      "a": [
        1
      ]
    }
  },
  {
    "he": "תזריע",
    "ref": {
      "b": 3,
      "c": 12,
      "v": 1,
      "a": [
        1
      ]
    }
  },
  {
    "he": "מצורע",
    "ref": {
      "b": 3,
      "c": 14,
      "v": 1,
      "a": [
        1
      ]
    }
  },
  {
    "he": "אחרי מות",
    "ref": {
      "b": 3,
      "c": 16,
      "v": 1,
      "a": [
        1
      ]
    }
  },
  {
    "he": "קדושים",
    "ref": {
      "b": 3,
      "c": 19,
      "v": 1,
      "a": [
        1
      ]
    }
  },
  {
    "he": "אמור",
    "ref": {
      "b": 3,
      "c": 21,
      "v": 1,
      "a": [
        1
      ]
    }
  },
  {
    "he": "בהר",
    "ref": {
      "b": 3,
      "c": 25,
      "v": 1,
      "a": [
        1
      ]
    }
  },
  {
    "he": "בחקתי",
    "ref": {
      "b": 3,
      "c": 26,
      "v": 3,
      "a": [
        1
      ]
    }
  },
  {
    "he": "במדבר",
    "ref": {
      "b": 4,
      "c": 1,
      "v": 1,
      "a": [
        1
      ]
    }
  },
  {
    "he": "נשא",
    "ref": {
      "b": 4,
      "c": 4,
      "v": 21,
      "a": [
        1
      ]
    }
  },
  {
    "he": "בהעלותך",
    "ref": {
      "b": 4,
      "c": 8,
      "v": 1,
      "a": [
        1
      ]
    }
  },
  {
    "he": "שלח",
    "ref": {
      "b": 4,
      "c": 13,
      "v": 1,
      "a": [
        1
      ]
    }
  },
  {
    "he": "קרח",
    "ref": {
      "b": 4,
      "c": 16,
      "v": 1,
      "a": [
        1
      ]
    }
  },
  {
    "he": "חקת",
    "ref": {
      "b": 4,
      "c": 19,
      "v": 1,
      "a": [
        1
      ]
    }
  },
  {
    "he": "בלק",
    "ref": {
      "b": 4,
      "c": 22,
      "v": 2,
      "a": [
        1
      ]
    }
  },
  {
    "he": "פנחס",
    "ref": {
      "b": 4,
      "c": 25,
      "v": 10,
      "a": [
        1
      ]
    }
  },
  {
    "he": "מטות",
    "ref": {
      "b": 4,
      "c": 30,
      "v": 2,
      "a": [
        1
      ]
    }
  },
  {
    "he": "מסעי",
    "ref": {
      "b": 4,
      "c": 33,
      "v": 1,
      "a": [
        1
      ]
    }
  },
  {
    "he": "דברים",
    "ref": {
      "b": 5,
      "c": 1,
      "v": 1,
      "a": [
        1
      ]
    }
  },
  {
    "he": "ואתחנן",
    "ref": {
      "b": 5,
      "c": 3,
      "v": 23,
      "a": [
        1
      ]
    }
  },
  {
    "he": "עקב",
    "ref": {
      "b": 5,
      "c": 7,
      "v": 12,
      "a": [
        1
      ]
    }
  },
  {
    "he": "ראה",
    "ref": {
      "b": 5,
      "c": 11,
      "v": 26,
      "a": [
        1
      ]
    }
  },
  {
    "he": "שופטים",
    "ref": {
      "b": 5,
      "c": 16,
      "v": 18,
      "a": [
        1
      ]
    }
  },
  {
    "he": "כי תצא",
    "ref": {
      "b": 5,
      "c": 21,
      "v": 10,
      "a": [
        1
      ]
    }
  },
  {
    "he": "כי תבוא",
    "ref": {
      "b": 5,
      "c": 26,
      "v": 1,
      "a": [
        1
      ]
    }
  },
  {
    "he": "נצבים",
    "ref": {
      "b": 5,
      "c": 29,
      "v": 9,
      "a": [
        1
      ]
    }
  },
  {
    "he": "וילך",
    "ref": {
      "b": 5,
      "c": 31,
      "v": 1,
      "a": [
        1
      ]
    }
  },
  {
    "he": "האזינו",
    "ref": {
      "b": 5,
      "c": 32,
      "v": 1,
      "a": [
        1
      ]
    }
  },
  {
    "he": "וזאת הברכה",
    "ref": {
      "b": 5,
      "c": 33,
      "v": 1,
      "a": [
        1
      ]
    }
  }
]